bencode/__init__.py
bencode/bencode_decoder.py
klik_bencode-0.1.dist-info/LICENSE
klik_bencode-0.1.dist-info/METADATA
klik_bencode-0.1.dist-info/WHEEL
klik_bencode-0.1.dist-info/top_level.txt
klik_bencode-0.1.dist-info/RECORD
