Metadata-Version: 2.1
Name: klik-bencode
Version: 0.1
Summary: To decode the Bencode string to Python native datatypes
Home-page: https://github.com/malhotraguy/klik_interview
Author: Rahul Malhotra
Author-email: electronicsgrad@gmail.com
License: MIT
Platform: UNKNOWN
Requires-Python: >=3.6
